{
  "schemaVersion": 1,
  "metadata": {
    "plugin": "obsidian-rapid-notes",
    "version": "1.0.1",
    "title": "Rapid Notes",
    "description": "Rapid Notes Localization & Tweaks",
    "language": "zh-cn",
    "supportedVersions": "1.2.6",
    "author": ""
  },
  "dict": {
    "main.js": {
      "ast": [
        {
          "type": "AssignmentExpression",
          "name": "innerText",
          "source": "Prefixed folders:",
          "target": "带前缀的文件夹："
        },
        {
          "type": "CallExpression",
          "name": "appendText",
          "source": "Keyword that will trigger the action (single words, case sensitive).",
          "target": "将触发操作的关键词（单个单词，区分大小写）。"
        },
        {
          "type": "CallExpression",
          "name": "appendText",
          "source": "Text that will be prepended to the filename. Can use placeholders such as {{date:YYYY-MM-DD}} (Moment.js formatting).",
          "target": "将添加到文件名前的文本。可以使用占位符，例如 {{date:YYYY-MM-DD}}（Moment.js 格式）。"
        },
        {
          "type": "CallExpression",
          "name": "appendText",
          "source": "Location for the saved note. Can use placeholders such as {{date:YYYY-MM-DD}} (Moment.js formatting).",
          "target": "保存笔记的位置。可以使用占位符，例如 {{date:YYYY-MM-DD}}（Moment.js 格式）。"
        },
        {
          "type": "CallExpression",
          "name": "appendText",
          "source": "Create a command to save directly into the folder.",
          "target": "创建一个命令以直接保存到文件夹。"
        },
        {
          "type": "CallExpression",
          "name": "appendText",
          "source": "Important: Command changes will show up in the command palette after an app relaunch or reenabling the plugin.",
          "target": "重要提示：命令更改将在应用重新启动或重新启用插件后显示在命令面板中。"
        },
        {
          "type": "CallExpression",
          "name": "createDiv",
          "source": "suggestion",
          "target": "suggestion"
        },
        {
          "type": "CallExpression",
          "name": "createEl",
          "source": "br",
          "target": "br"
        },
        {
          "type": "CallExpression",
          "name": "setName",
          "source": "Force file creation adding a number at the end if the folder/filename is already in use. Default behavior will open the existing file.",
          "target": "如果文件夹/文件名已被使用，强制创建文件并在末尾添加数字。默认行为将打开现有文件。"
        },
        {
          "type": "CallExpression",
          "name": "setName",
          "source": "Show prefix list in note creation modal.",
          "target": "在笔记创建模态框中显示前缀列表。"
        },
        {
          "type": "CallExpression",
          "name": "setName",
          "source": "Escape symbol to avoid checking the prefix and moving the note.",
          "target": "用于避免检查前缀和移动笔记的转义符号。"
        },
        {
          "type": "CallExpression",
          "name": "setName",
          "source": "Optional separator between the prefix and the filename (space character by default).",
          "target": "前缀和文件名之间的可选分隔符（默认为空格字符）。"
        },
        {
          "type": "CallExpression",
          "name": "setName",
          "source": "Capitalize note name and new folders.",
          "target": "将笔记名称和新文件夹首字母大写。"
        },
        {
          "type": "CallExpression",
          "name": "setName",
          "source": "Add new prefixes or create command shortcuts for saving directly into folders.",
          "target": "添加新前缀或创建用于直接保存到文件夹的命令快捷方式。"
        },
        {
          "type": "CallExpression",
          "name": "setPlaceholder",
          "source": "Prefix",
          "target": "前缀"
        },
        {
          "type": "CallExpression",
          "name": "setPlaceholder",
          "source": "Real prefix",
          "target": "实际前缀"
        },
        {
          "type": "CallExpression",
          "name": "setPlaceholder",
          "source": "Folder",
          "target": "文件夹"
        },
        {
          "type": "CallExpression",
          "name": "setTooltip",
          "source": "Add additional prefix",
          "target": "添加额外前缀"
        },
        {
          "type": "CallExpression",
          "name": "setTooltip",
          "source": "Move up",
          "target": "上移"
        },
        {
          "type": "CallExpression",
          "name": "setTooltip",
          "source": "Move down",
          "target": "下移"
        },
        {
          "type": "CallExpression",
          "name": "setTooltip",
          "source": "Delete",
          "target": "删除"
        },
        {
          "type": "NewExpression",
          "name": "Notice",
          "source": "Rapid notes: The custom command needs an Obsidian relaunch to work properly.",
          "target": "快速笔记：自定义命令需要重新启动 Obsidian 才能正常工作。"
        },
        {
          "type": "NewExpression",
          "name": "Notice",
          "source": "Rapid notes: The custom command will be removed after Obsidian relaunches.",
          "target": "快速笔记：自定义命令将在 Obsidian 重新启动后被移除。"
        },
        {
          "type": "NewExpression",
          "name": "Notice",
          "source": "Prefix already used!",
          "target": "前缀已被使用！"
        },
        {
          "type": "NewExpression",
          "name": "Notice",
          "source": "Prefixes can't contain spaces!",
          "target": "前缀不能包含空格！"
        },
        {
          "type": "NewExpression",
          "name": "Notice",
          "source": "This folder already has a prefix associated with it.",
          "target": "此文件夹已有关联的前缀。"
        },
        {
          "type": "ObjectProperty",
          "name": "name",
          "source": "arrow",
          "target": "arrow"
        },
        {
          "type": "ObjectProperty",
          "name": "name",
          "source": "flip",
          "target": "flip"
        },
        {
          "type": "ObjectProperty",
          "name": "name",
          "source": "hide",
          "target": "hide"
        },
        {
          "type": "ObjectProperty",
          "name": "name",
          "source": "offset",
          "target": "offset"
        },
        {
          "type": "ObjectProperty",
          "name": "name",
          "source": "New note in current tab",
          "target": "在当前标签页新建笔记"
        },
        {
          "type": "ObjectProperty",
          "name": "name",
          "source": "New note in new tab",
          "target": "在新标签页新建笔记"
        },
        {
          "type": "ObjectProperty",
          "name": "name",
          "source": "New note in background tab",
          "target": "在后台标签页新建笔记"
        },
        {
          "type": "ObjectProperty",
          "name": "name",
          "source": "New note in new pane",
          "target": "在新窗格新建笔记"
        },
        {
          "type": "ObjectProperty",
          "name": "name",
          "source": "New note in new window",
          "target": "在新窗口中新建笔记"
        },
        {
          "type": "ObjectProperty",
          "name": "name",
          "source": "New inline note (open in new tab)",
          "target": "新建内联笔记（在新标签页中打开）"
        },
        {
          "type": "ObjectProperty",
          "name": "name",
          "source": "New inline note (open in background tab)",
          "target": "新建内联笔记（在后台标签页中打开）"
        },
        {
          "type": "ObjectProperty",
          "name": "name",
          "source": "New inline note (open in new pane)",
          "target": "新建内联笔记（在新窗格中打开）"
        },
        {
          "type": "ObjectProperty",
          "name": "name",
          "source": "New inline note (open in new window)",
          "target": "新建内联笔记（在新窗口中打开）"
        },
        {
          "type": "ObjectProperty",
          "name": "text",
          "source": "Rapid Notes settings",
          "target": "快速笔记设置"
        },
        {
          "type": "ObjectProperty",
          "name": "text",
          "source": "[New!] Now you can also create notes and link to them directly from the editor while typing using the plugin inline commands. You can trigger the command while the cursor is inside the link in double brackets, or just by selecting any text in the editor.",
          "target": "[新功能！] 现在您还可以在编辑器中输入时，通过插件内联命令直接创建笔记并链接到它们。您可以在双括号内的链接中触发命令，或者只需在编辑器中选择任何文本。"
        },
        {
          "type": "ObjectProperty",
          "name": "text",
          "source": "Prefix: ",
          "target": "前缀："
        },
        {
          "type": "ObjectProperty",
          "name": "text",
          "source": "Real prefix (optional): ",
          "target": "实际前缀（可选）："
        },
        {
          "type": "ObjectProperty",
          "name": "text",
          "source": "Folder: ",
          "target": "文件夹："
        },
        {
          "type": "ObjectProperty",
          "name": "text",
          "source": "Toggle: ",
          "target": "切换："
        },
        {
          "type": "VariableDeclarator",
          "name": "placeholder",
          "source": "New note",
          "target": "新建笔记"
        }
      ],
      "regex": []
    }
  }
}