{
  "schemaVersion": 1,
  "metadata": {
    "plugin": "table-checkbox-row-color",
    "version": "1.0.0",
    "title": "Table Checkbox Row Color",
    "description": "Table Checkbox Row Color Localization & Tweaks",
    "language": "zh-cn",
    "supportedVersions": "1.0.7",
    "author": ""
  },
  "dict": {
    "main.js": {
      "ast": [
        {
          "type": "CallExpression",
          "name": "setDesc",
          "source": "Choose the color used to tint checked table rows in Reading Mode.",
          "target": "选择用于在阅读模式下为已勾选的表格行着色的颜色。"
        },
        {
          "type": "CallExpression",
          "name": "setDesc",
          "source": "Apply a strikethrough to the row text when at least one checkbox in that row is checked.",
          "target": "当一行中至少有一个复选框被勾选时，对该行文本应用删除线。"
        },
        {
          "type": "CallExpression",
          "name": "setName",
          "source": "Row highlight color",
          "target": "行高亮颜色"
        },
        {
          "type": "CallExpression",
          "name": "setName",
          "source": "Strike through checked rows",
          "target": "为已勾选行添加删除线"
        }
      ],
      "regex": []
    }
  }
}