{
  "schemaVersion": 1,
  "metadata": {
    "plugin": "edit-in-neovim",
    "version": "1.0.0",
    "title": "Edit in Neovim",
    "description": "Edit in Neovim Localization & Tweaks",
    "language": "zh-cn",
    "supportedVersions": "1.8.5",
    "author": ""
  },
  "dict": {
    "main.js": {
      "ast": [
        {
          "type": "CallExpression",
          "name": "error",
          "source": "[winston] Unknown logger level: %s",
          "target": "[winston] 未知的日志级别：%s"
        },
        {
          "type": "CallExpression",
          "name": "error",
          "source": "assertion failed",
          "target": "断言失败"
        },
        {
          "type": "CallExpression",
          "name": "error",
          "source": "failed request to \"%s\": %s: %s",
          "target": "对“%s”的请求失败：%s：%s"
        },
        {
          "type": "CallExpression",
          "name": "error",
          "source": "Tabpage does not have `getOption`",
          "target": "标签页没有 `getOption`"
        },
        {
          "type": "CallExpression",
          "name": "error",
          "source": "Tabpage does not have `setOption`",
          "target": "标签页没有 `setOption`"
        },
        {
          "type": "CallExpression",
          "name": "error",
          "source": "Unhandled event: %s",
          "target": "未处理的事件：%s"
        },
        {
          "type": "CallExpression",
          "name": "error",
          "source": "Could not get vim api results",
          "target": "无法获取 vim API 结果"
        },
        {
          "type": "CallExpression",
          "name": "error",
          "source": "Could not dynamically generate neovim API: %s: %O",
          "target": "无法动态生成 neovim API：%s：%O"
        },
        {
          "type": "CallExpression",
          "name": "error",
          "source": "Neovim RPC connection failed after spawn:",
          "target": "Neovim RPC 连接在启动后失败："
        },
        {
          "type": "CallExpression",
          "name": "error",
          "source": "Error caught during child_process.spawn call itself:",
          "target": "在 child_process.spawn 调用本身期间捕获到错误："
        },
        {
          "type": "CallExpression",
          "name": "error",
          "source": "Error opening file in neovim",
          "target": "在 neovim 中打开文件时出错"
        },
        {
          "type": "CallExpression",
          "name": "info",
          "source": "handleRequest (queued): %s",
          "target": "handleRequest（已排队）：%s"
        },
        {
          "type": "CallExpression",
          "name": "info",
          "source": "handleRequest: %s",
          "target": "handleRequest：%s"
        },
        {
          "type": "CallExpression",
          "name": "info",
          "source": "handleNotification: %s",
          "target": "handleNotification：%s"
        },
        {
          "type": "CallExpression",
          "name": "info",
          "source": "nvim disconnected",
          "target": "nvim 已断开连接"
        },
        {
          "type": "CallExpression",
          "name": "setDesc",
          "source": "Open the Neovim instance when Obsidian opens",
          "target": "当 Obsidian 打开时启动 Neovim 实例"
        },
        {
          "type": "CallExpression",
          "name": "setDesc",
          "source": "Which file extensions do you want this extension to try and open?",
          "target": "您希望此扩展尝试打开哪些文件扩展名？"
        },
        {
          "type": "CallExpression",
          "name": "setDesc",
          "source": "Manual override for detecting nvim binary. It's recommended you add nvim to your PATH instead. (requires reload)",
          "target": "手动覆盖以检测 nvim 二进制文件。建议您将 nvim 添加到 PATH 中。（需要重新加载）"
        },
        {
          "type": "CallExpression",
          "name": "setDesc",
          "source": "If you have a specific neovim distro you'd like to use (lazyvim for example), leave blank to use your default neovim config.",
          "target": "如果您有特定的 neovim 发行版想要使用（例如 lazyvim），请留空以使用默认的 neovim 配置。"
        },
        {
          "type": "CallExpression",
          "name": "setDesc",
          "source": "The Neovim instance will be spawned using --listen and needs a socket or IP:PORT (not sure if sockets work so use at your own risk)",
          "target": "Neovim 实例将使用 --listen 启动，并需要一个套接字或 IP:PORT（不确定套接字是否有效，请自行承担风险）"
        },
        {
          "type": "CallExpression",
          "name": "setName",
          "source": "Open on startup",
          "target": "启动时打开"
        },
        {
          "type": "CallExpression",
          "name": "setName",
          "source": "Headless",
          "target": "无头模式"
        },
        {
          "type": "CallExpression",
          "name": "setName",
          "source": "Supported file types",
          "target": "支持的文件类型"
        },
        {
          "type": "CallExpression",
          "name": "setName",
          "source": "Terminal Path",
          "target": "终端路径"
        },
        {
          "type": "CallExpression",
          "name": "setName",
          "source": "Path to Neovim binary",
          "target": "Neovim 二进制文件路径"
        },
        {
          "type": "CallExpression",
          "name": "setName",
          "source": "Neovim server location",
          "target": "Neovim 服务器位置"
        },
        {
          "type": "CallExpression",
          "name": "setPlaceholder",
          "source": "Filetypes should be separated by spaces and not include the '.', E.g. 'txt md css html'",
          "target": "文件类型应以空格分隔且不包含 '.'，例如 'txt md css html'"
        },
        {
          "type": "CallExpression",
          "name": "setPlaceholder",
          "source": "E.g. /usr/bin/kitty, /Applications/iTerm.app/Contents/MacOS/iTerm2...",
          "target": "例如 /usr/bin/kitty, /Applications/iTerm.app/Contents/MacOS/iTerm2..."
        },
        {
          "type": "CallExpression",
          "name": "setPlaceholder",
          "source": "lazyvim, my_writing_config, etc.",
          "target": "lazyvim, my_writing_config 等。"
        },
        {
          "type": "CallExpression",
          "name": "warn",
          "source": "winston: exitOnError cannot be true with no exception handlers.",
          "target": "winston: 在没有异常处理器的情况下，exitOnError 不能为 true。"
        },
        {
          "type": "CallExpression",
          "name": "warn",
          "source": "winston: not exiting process.",
          "target": "winston: 不退出进程。"
        },
        {
          "type": "CallExpression",
          "name": "warn",
          "source": "winston: exitOnError cannot be true with no rejection handlers.",
          "target": "winston: 在没有拒绝处理器的情况下，exitOnError 不能为 true。"
        },
        {
          "type": "CallExpression",
          "name": "warn",
          "source": "Callback function no longer supported as of winston@3.0.0",
          "target": "自 winston@3.0.0 起不再支持回调函数"
        },
        {
          "type": "CallExpression",
          "name": "warn",
          "source": "Level \"log\" not defined: conflicts with the method \"log\". Use a different level name.",
          "target": "级别“log”未定义：与方法“log”冲突。请使用不同的级别名称。"
        },
        {
          "type": "CallExpression",
          "name": "warn",
          "source": "`clearHighlight` is deprecated, use ``clearNamespace()` instead",
          "target": "`clearHighlight` 已弃用，请使用 `clearNamespace()` 代替"
        },
        {
          "type": "CallExpression",
          "name": "warn",
          "source": "No valid neovim binary resolved, plugin will likely not function",
          "target": "未找到有效的 neovim 二进制文件，插件可能无法正常工作"
        },
        {
          "type": "ObjectProperty",
          "name": "description",
          "source": "A logger for just about everything.",
          "target": "一个几乎可以记录一切的日志记录器。"
        },
        {
          "type": "ObjectProperty",
          "name": "message",
          "source": "Request Timeout",
          "target": "请求超时"
        },
        {
          "type": "ObjectProperty",
          "name": "name",
          "source": "Buffer",
          "target": "缓冲区"
        },
        {
          "type": "ObjectProperty",
          "name": "name",
          "source": "Window",
          "target": "窗口"
        },
        {
          "type": "ObjectProperty",
          "name": "name",
          "source": "Tabpage",
          "target": "标签页"
        },
        {
          "type": "ObjectProperty",
          "name": "name",
          "source": "MacBook Air",
          "target": "MacBook Air"
        },
        {
          "type": "ObjectProperty",
          "name": "name",
          "source": "MacBook Pro",
          "target": "MacBook Pro"
        },
        {
          "type": "ObjectProperty",
          "name": "name",
          "source": "MacBook",
          "target": "MacBook"
        },
        {
          "type": "ObjectProperty",
          "name": "name",
          "source": "Mac Studio",
          "target": "Mac Studio"
        },
        {
          "type": "ObjectProperty",
          "name": "name",
          "source": "Mac mini",
          "target": "Mac mini"
        },
        {
          "type": "ObjectProperty",
          "name": "name",
          "source": "iMac Pro",
          "target": "iMac Pro"
        },
        {
          "type": "ObjectProperty",
          "name": "name",
          "source": "Mac Pro",
          "target": "Mac Pro"
        },
        {
          "type": "ObjectProperty",
          "name": "name",
          "source": "Mac Pro Server",
          "target": "Mac Pro Server"
        },
        {
          "type": "ObjectProperty",
          "name": "name",
          "source": "Open Neovim",
          "target": "打开 Neovim"
        },
        {
          "type": "ObjectProperty",
          "name": "name",
          "source": "Close Neovim",
          "target": "关闭 Neovim"
        },
        {
          "type": "ObjectProperty",
          "name": "name",
          "source": "Open File",
          "target": "打开文件"
        }
      ],
      "regex": []
    }
  }
}