{
  "schemaVersion": 1,
  "metadata": {
    "plugin": "askify-obsidian-sync",
    "version": "1.0.0",
    "title": "Askify Sync",
    "description": "Askify Sync Localization & Tweaks",
    "language": "zh-cn",
    "supportedVersions": "1.0.3",
    "author": ""
  },
  "dict": {
    "main.js": {
      "ast": [
        {
          "type": "CallExpression",
          "name": "log",
          "source": "error in unzipping the file",
          "target": "解压文件时出错"
        },
        {
          "type": "CallExpression",
          "name": "log",
          "source": "plugin loadded..",
          "target": "插件已加载.."
        },
        {
          "type": "CallExpression",
          "name": "log",
          "source": "sync initiated",
          "target": "同步已启动"
        },
        {
          "type": "CallExpression",
          "name": "log",
          "source": "error in creating the folder",
          "target": "创建文件夹时出错"
        },
        {
          "type": "CallExpression",
          "name": "log",
          "source": "Unable to delete file",
          "target": "无法删除文件"
        },
        {
          "type": "CallExpression",
          "name": "log",
          "source": "preparing for api call",
          "target": "正在准备 API 调用"
        },
        {
          "type": "CallExpression",
          "name": "log",
          "source": "starting the download",
          "target": "开始下载"
        },
        {
          "type": "CallExpression",
          "name": "log",
          "source": "error in creating file",
          "target": "创建文件时出错"
        },
        {
          "type": "CallExpression",
          "name": "log",
          "source": "file created",
          "target": "文件已创建"
        },
        {
          "type": "CallExpression",
          "name": "log",
          "source": "fie data is null",
          "target": "文件数据为空"
        },
        {
          "type": "CallExpression",
          "name": "setDesc",
          "source": "Get this key from the Askify website",
          "target": "从 Askify 网站获取此密钥"
        },
        {
          "type": "CallExpression",
          "name": "setDesc",
          "source": "Enter the folder path where you want to sync the notes",
          "target": "输入您想要同步笔记的文件夹路径"
        },
        {
          "type": "CallExpression",
          "name": "setName",
          "source": "Askify Obsidian sync key",
          "target": "Askify Obsidian 同步密钥"
        },
        {
          "type": "CallExpression",
          "name": "setName",
          "source": "Askify Local Folder Path",
          "target": "Askify 本地文件夹路径"
        },
        {
          "type": "CallExpression",
          "name": "setPlaceholder",
          "source": "Enter your key",
          "target": "输入您的密钥"
        },
        {
          "type": "CallExpression",
          "name": "setPlaceholder",
          "source": "Example: Inbox/Askify",
          "target": "示例：Inbox/Askify"
        },
        {
          "type": "NewExpression",
          "name": "Notice",
          "source": "Askify Sync started",
          "target": "Askify 同步已启动"
        },
        {
          "type": "NewExpression",
          "name": "Notice",
          "source": "Askify Sync Failed! Please add the Askify sync key in the plugin settings.",
          "target": "Askify 同步失败！请在插件设置中添加 Askify 同步密钥。"
        },
        {
          "type": "NewExpression",
          "name": "Notice",
          "source": "Sync complete",
          "target": "同步完成"
        },
        {
          "type": "NewExpression",
          "name": "Notice",
          "source": "Free limit of 12 Syncs reached! Upgrade to Askify Essential for unlimited syncs",
          "target": "已达到 12 次同步的免费限制！升级到 Askify Essential 以获得无限同步"
        },
        {
          "type": "NewExpression",
          "name": "Notice",
          "source": "Please add correct Askify sync key",
          "target": "请添加正确的 Askify 同步密钥"
        },
        {
          "type": "ObjectProperty",
          "name": "text",
          "source": "Settings for Askify Sync plugin.",
          "target": "Askify 同步插件的设置。"
        }
      ],
      "regex": []
    }
  }
}