{
  "schemaVersion": 1,
  "metadata": {
    "plugin": "callout-integrator",
    "version": "1.0.1",
    "title": "Callout Integrator",
    "description": "Callout Integrator Localization & Tweaks",
    "language": "zh-cn",
    "supportedVersions": "1.1.4",
    "author": ""
  },
  "dict": {
    "main.js": {
      "ast": [
        {
          "type": "ObjectProperty",
          "name": "name",
          "source": "integrate",
          "target": "集成"
        }
      ],
      "regex": []
    }
  }
}